{
    "textures": {
        "stone_lattice": "shaded_citadels:block/stone_lattice",
        "particle": "shaded_citadels:block/stone_lattice"
    },
    "elements": [
        {
            "from": [ 0, 0, 0 ], 
            "to": [ 5, 5, 16 ], 
            "faces": {
                "north": { "texture": "#stone_lattice", "uv": [ 11, 11, 16, 16 ], "cullface": "north" },
                "south": { "texture": "#stone_lattice", "uv": [ 0, 11, 5, 16 ], "cullface": "south" },
                "west": { "texture": "#stone_lattice", "uv": [ 0, 11, 16, 16 ], "cullface": "west" },
                "down": { "texture": "#stone_lattice", "uv": [ 0, 0, 5, 16 ], "cullface": "down" }
            }
        },
        {
            "from": [ 11, 0, 0 ], 
            "to": [ 16, 5, 16 ], 
            "faces": {
                "north": { "texture": "#stone_lattice", "uv": [ 0, 11, 5, 16 ], "cullface": "north" },
                "east": { "texture": "#stone_lattice", "uv": [ 0, 11, 16, 16 ], "cullface": "east" },
                "south": { "texture": "#stone_lattice", "uv": [ 11, 11, 16, 16 ], "cullface": "south" },
                "down": { "texture": "#stone_lattice", "uv": [ 11, 0, 16, 16 ], "cullface": "down" }
            }
        },
        {
            "from": [ 0, 11, 0 ], 
            "to": [ 16, 16, 5 ], 
            "faces": {
                "north": { "texture": "#stone_lattice", "uv": [ 0, 0, 16, 5 ], "cullface": "north" },
                "east": { "texture": "#stone_lattice", "uv": [ 11, 0, 16, 5 ], "cullface": "east" },
                "west": { "texture": "#stone_lattice", "uv": [ 0, 0, 5, 5 ], "cullface": "west" },
                "up": { "texture": "#stone_lattice", "uv": [ 0, 0, 16, 5 ], "cullface": "up" }
            }
        },
        {
            "from": [ 0, 11, 11 ], 
            "to": [ 16, 16, 16 ], 
            "faces": {
                "east": { "texture": "#stone_lattice", "uv": [ 0, 0, 5, 5 ], "cullface": "east" },
                "south": { "texture": "#stone_lattice", "uv": [ 0, 0, 16, 5 ], "cullface": "south" },
                "west": { "texture": "#stone_lattice", "uv": [ 11, 0, 16, 5 ], "cullface": "west" },
                "up": { "texture": "#stone_lattice", "uv": [ 0, 11, 16, 16 ], "cullface": "up" }
            }
        },
        {
            "from": [ 5, 0, 0 ], 
            "to": [ 11, 5, 5 ], 
            "faces": {
                "north": { "texture": "#stone_lattice", "uv": [ 5, 11, 11, 16 ], "cullface": "north" },
                "down": { "texture": "#stone_lattice", "uv": [ 5, 11, 11, 16 ], "cullface": "down" }
            }
        },
        {
            "from": [ 5, 0, 11 ], 
            "to": [ 11, 5, 16 ], 
            "faces": {
                "south": { "texture": "#stone_lattice", "uv": [ 5, 11, 11, 16 ], "cullface": "south" },
                "down": { "texture": "#stone_lattice", "uv": [ 5, 11, 11, 16 ], "cullface": "down" }
            }
        },
        {
            "from": [ 0, 5, 0 ], 
            "to": [ 5, 11, 5 ], 
            "faces": {
                "north": { "texture": "#stone_lattice", "uv": [ 11, 5, 16, 11 ], "cullface": "north" },
                "west": { "texture": "#stone_lattice", "uv": [ 0, 5, 5, 11 ], "cullface": "west" }
            }
        },
        {
            "from": [ 11, 5, 0 ], 
            "to": [ 16, 11, 5 ], 
            "faces": {
                "north": { "texture": "#stone_lattice", "uv": [ 0, 5, 5, 11 ], "cullface": "north" },
                "east": { "texture": "#stone_lattice", "uv": [ 11, 5, 16, 11 ], "cullface": "east" }
            }
        },
        {
            "from": [ 11, 5, 11 ], 
            "to": [ 16, 11, 16 ], 
            "faces": {
                "east": { "texture": "#stone_lattice", "uv": [ 0, 5, 5, 11 ], "cullface": "east" },
                "south": { "texture": "#stone_lattice", "uv": [ 11, 5, 16, 11 ], "cullface": "south" }
            }
        },
        {
            "from": [ 0, 5, 11 ], 
            "to": [ 5, 11, 16 ], 
            "faces": {
                "south": { "texture": "#stone_lattice", "uv": [ 0, 5, 5, 11 ], "cullface": "south" },
                "west": { "texture": "#stone_lattice", "uv": [ 11, 5, 16, 11 ], "cullface": "west" }
            }
        },
        {
            "from": [ 0, 11, 5 ], 
            "to": [ 5, 16, 11 ], 
            "faces": {
                "west": { "texture": "#stone_lattice", "uv": [ 5, 0, 11, 5 ], "cullface": "west" },
                "up": { "texture": "#stone_lattice", "uv": [ 0, 5, 5, 11 ], "cullface": "up" }
            }
        },
        {
            "from": [ 11, 11, 5 ], 
            "to": [ 16, 16, 11 ], 
            "faces": {
                "east": { "texture": "#stone_lattice", "uv": [ 5, 0, 11, 5 ], "cullface": "east" },
                "up": { "texture": "#stone_lattice", "uv": [ 11, 5, 16, 11 ], "cullface": "up" }
            }
        }
    ]
}